Workbook

Sheet Reconciliation
A1: Kape Luntian Cafe - Bank Reconciliation Statement
A2: As of August 31, 2026 | Sample data, fictional company
A4: BANK SIDE
A5: Balance per bank statement | B5: ='Bank Statement'!E19 -> 233615.6
A6: Add: Deposit in transit (DEP-0831, Aug 31) | B6: ='Cash Book'!D18 -> 36200
A7: Less: Outstanding checks
A8: CHK 2006 - Espresso machine repair | B8: ='Cash Book'!E16 -> 9300
A9: CHK 2007 - Milk and syrups | B9: ='Cash Book'!E17 -> 14625
A10: Adjusted bank balance | B10: =B5+B6-SUM(B8:B9) -> 245890.6
A12: BOOK SIDE
A13: Balance per books | B13: ='Cash Book'!F19 -> 258145
A14: Add: Interest earned | B14: ='Bank Statement'!D18 -> 85.6
A15: Less: NSF check returned - R. Dizon catering | B15: ='Bank Statement'!C16 -> 12000
A16: Less: Bank service charge | B16: ='Bank Statement'!C17 -> 250
A17: Less: Error on CHK 2003 (recorded 1,450; bank cleared 1,540) | B17: ='Bank Statement'!C10-'Cash Book'!E10 -> 90
A18: Adjusted book balance | B18: =B13+B14-B15-B16-B17 -> 245890.6
A20: Status | B20: =IF(ROUND(B10-B18,2)=0,"Reconciled","Difference: "&TEXT(B10-B18,"#,##0.00")) -> Reconciled
A22: ADJUSTING JOURNAL ENTRIES (book side)
A23: Account | B23: Debit | C23: Credit
A24: 1) Cash in Bank | B24: =B14 -> 85.6
A25: Interest Income | C25: =B14 -> 85.6
A26: 2) Accounts Receivable - R. Dizon | B26: =B15 -> 12000
A27: Cash in Bank | C27: =B15 -> 12000
A28: 3) Bank Service Charge Expense | B28: =B16 -> 250
A29: Cash in Bank | C29: =B16 -> 250
A30: 4) Utilities Expense | B30: =B17 -> 90
A31: Cash in Bank | C31: =B17 -> 90
A32: Total | B32: =SUM(B24:B31) -> 12425.6 | C32: =SUM(C24:C31) -> 12425.6
A34: No entry is needed for the deposit in transit or the outstanding checks: the bank will record them next month.

Sheet Cash Book
A1: Kape Luntian Cafe (fictional) - Cash in Bank ledger, August 2026
A2: What the cafe recorded in its own books.
A4: Date | B4: Reference | C4: Description | D4: Debit (in) | E4: Credit (out) | F4: Balance
A5: 46235 | C5: Beginning balance | F5: 150000
A6: 46237 | B6: DEP-0803 | C6: Deposit of cash sales | D6: 45000 | F6: 195000
A7: 46239 | B7: CHK 2001 | C7: Rent - Dagatan Commercial Space | E7: 25000 | F7: 170000
A8: 46242 | B8: CHK 2002 | C8: Coffee beans - Batangas Bean Traders | E8: 18450 | F8: 151550
A9: 46244 | B9: DEP-0810 | C9: Deposit of cash sales | D9: 38500 | F9: 190050
A10: 46246 | B10: CHK 2003 | C10: Electricity - August bill | E10: 1450 | F10: 188600
A11: 46249 | B11: CHK 2004 | C11: Payroll - Aug 1 to 15 | E11: 42000 | F11: 146600
A12: 46251 | B12: DEP-0817 | C12: Deposit of cash sales | D12: 52300 | F12: 198900
A13: 46254 | B13: DEP-0820 | C13: Deposit of customer check - R. Dizon catering | D13: 12000 | F13: 210900
A14: 46256 | B14: CHK 2005 | C14: Cups, lids and napkins - Cavite Supplies | E14: 6780 | F14: 204120
A15: 46258 | B15: DEP-0824 | C15: Deposit of cash sales | D15: 41750 | F15: 245870
A16: 46262 | B16: CHK 2006 | C16: Espresso machine repair | E16: 9300 | F16: 236570
A17: 46264 | B17: CHK 2007 | C17: Milk and syrups - Tagaytay Dairy | E17: 14625 | F17: 221945
A18: 46265 | B18: DEP-0831 | C18: Deposit of cash sales | D18: 36200 | F18: 258145
C19: Ending balance per books | F19: 258145

Sheet Bank Statement
A1: Sample Bank, Checking Account No. 0000-1234-56 - Statement for August 2026
A2: Account name: Kape Luntian Cafe (fictional). What the bank recorded.
A4: Date | B4: Description | C4: Withdrawals | D4: Deposits | E4: Balance
A5: 46235 | B5: Beginning balance | E5: 150000
A6: 46237 | B6: Deposit | D6: 45000 | E6: 195000
A7: 46240 | B7: Check No. 2001 | C7: 25000 | E7: 170000
A8: 46244 | B8: Deposit | D8: 38500 | E8: 208500
A9: 46245 | B9: Check No. 2002 | C9: 18450 | E9: 190050
A10: 46248 | B10: Check No. 2003 | C10: 1540 | E10: 188510
A11: 46250 | B11: Check No. 2004 | C11: 42000 | E11: 146510
A12: 46251 | B12: Deposit | D12: 52300 | E12: 198810
A13: 46254 | B13: Deposit | D13: 12000 | E13: 210810
A14: 46258 | B14: Deposit | D14: 41750 | E14: 252560
A15: 46259 | B15: Check No. 2005 | C15: 6780 | E15: 245780
A16: 46260 | B16: Returned check - insufficient funds (R. Dizon) | C16: 12000 | E16: 233780
A17: 46265 | B17: Monthly service charge | C17: 250 | E17: 233530
A18: 46265 | B18: Interest earned | D18: 85.6 | E18: 233615.6
B19: Ending balance per bank | E19: 233615.6
