Workbook

Sheet Summary
A1: Email Management - Shift Summary
A2: Monday, September 28, 2026 | Calculated from the Inbox Log tab | Sample data
A4: Label | B4: Emails | D4: Status | E4: Emails
A5: 1-Urgent | B5: =COUNTIF('Inbox Log'!$D$5:$D$24,A5) -> 3 | D5: Not started | E5: =COUNTIF('Inbox Log'!$G$5:$G$24,D5) -> 1
A6: 2-Clients | B6: =COUNTIF('Inbox Log'!$D$5:$D$24,A6) -> 6 | D6: In progress | E6: =COUNTIF('Inbox Log'!$G$5:$G$24,D6) -> 2
A7: 3-Finance | B7: =COUNTIF('Inbox Log'!$D$5:$D$24,A7) -> 3 | D7: Waiting | E7: =COUNTIF('Inbox Log'!$G$5:$G$24,D7) -> 2
A8: 4-Orders | B8: =COUNTIF('Inbox Log'!$D$5:$D$24,A8) -> 3 | D8: Done | E8: =COUNTIF('Inbox Log'!$G$5:$G$24,D8) -> 15
A9: 5-Team | B9: =COUNTIF('Inbox Log'!$D$5:$D$24,A9) -> 3
A10: 6-Newsletters | B10: =COUNTIF('Inbox Log'!$D$5:$D$24,A10) -> 2
A11: 7-Waiting | B11: =COUNTIF('Inbox Log'!$D$5:$D$24,A11) -> 0
A12: Total | B12: =SUM(B5:B11) -> 20
A15: Average reply time (hours) | B15: =ROUND(AVERAGE('Inbox Log'!I5:I24),1) -> 1.1
A16: Replies on time | B16: =COUNTIF('Inbox Log'!K5:K24,"On time")&" of "&(COUNTIF('Inbox Log'!K5:K24,"On time")+COUNTIF('Inbox Log'!K5:K24,"Late")) -> 11 of 12
A17: Still open at end of shift | B17: =COUNTIF('Inbox Log'!G5:G24,"<>Done") -> 5

Sheet Label System
A1: Inbox Label System and Filter Rules
A2: How every incoming email gets sorted, and how fast it must be answered | Sample setup
A4: Label | B4: What goes here | C4: Color | D4: Automatic filter rule | F4: Reply target (hours)
A5: 1-Urgent | B5: Payment problems, bank alerts, anything a client marks urgent | C5: Red | D5: Subject has "urgent" OR from the bank OR from a VIP client | F5: 2
A6: 2-Clients | B6: All customer and client emails | C6: Blue | D6: From any address on the client list | F6: 24
A7: 3-Finance | B7: Invoices, receipts, supplier price notices | C7: Green | D7: Subject has "invoice", "receipt" or "statement" | F7: 48
A8: 4-Orders | B8: Shopee, Lazada and website order notices | C8: Orange | D8: From the marketplace notification addresses | F8: Process same day
A9: 5-Team | B9: Internal updates and reminders | C9: Purple | D9: From the company's own email domain | F9: 24
A10: 6-Newsletters | B10: Promos, subscriptions, tips | C10: Gray | D10: Email has an "unsubscribe" link, skip the inbox | F10: No reply
A11: 7-Waiting | B11: Emails we sent and are waiting on a reply to | C11: Yellow | D11: Added by hand after sending | F11: Follow up after 3 days
A13: DAILY INBOX ROUTINE
A14: 1. Check the inbox 3 times a day: start of shift, middle, and 1 hour before the end.
A15: 2. Handle 1-Urgent first, then 2-Clients, then everything else.
A16: 3. If a reply takes under 2 minutes, answer it right away.
A17: 4. Anything waiting on someone else gets the 7-Waiting label and a follow-up date.
A18: 5. End of shift: every email is labeled, and the log below is updated.

Sheet Inbox Log
A1: Inbox Log - Monday, September 28, 2026
A2: Every email received in one shift, how it was handled, and whether the reply was on time
A4: Received | B4: From | C4: Subject | D4: Label | E4: Priority | F4: Action taken | G4: Status | H4: Replied at | I4: Reply time (hours) | J4: Target (hours) | K4: On time?
A5: 46293.337 | B5: billing@tagaytaywellness.ph | C5: URGENT: Payment failed for September invoice | D5: 1-Urgent | E5: High | F5: Replied, sent new payment link | G5: Done | H5: 46293.361 | I5: =IF(H5="","",ROUND((H5-A5)*24,1)) -> 0.6 | J5: =INDEX('Label System'!$F$5:$F$11,MATCH(D5,'Label System'!$A$5:$A$11,0)) -> 2 | K5: =IF(OR(I5="",NOT(ISNUMBER(J5))),"-",IF(I5<=J5,"On time","Late")) -> On time
A6: 46293.342 | B6: no-reply@shopee.ph | C6: New order #2409280123 | D6: 4-Orders | E6: Medium | F6: Order processed and packed | G6: Done | I6: =IF(H6="","",ROUND((H6-A6)*24,1)) | J6: =INDEX('Label System'!$F$5:$F$11,MATCH(D6,'Label System'!$A$5:$A$11,0)) -> Process same day | K6: =IF(OR(I6="",NOT(ISNUMBER(J6))),"-",IF(I6<=J6,"On time","Late")) -> -
A7: 46293.347 | B7: carla.mendoza@yahoo.com | C7: Where is my order ORD-10712? | D7: 2-Clients | E7: High | F7: Replied with tracking link | G7: Done | H7: 46293.378 | I7: =IF(H7="","",ROUND((H7-A7)*24,1)) -> 0.8 | J7: =INDEX('Label System'!$F$5:$F$11,MATCH(D7,'Label System'!$A$5:$A$11,0)) -> 24 | K7: =IF(OR(I7="",NOT(ISNUMBER(J7))),"-",IF(I7<=J7,"On time","Late")) -> On time
A8: 46293.355 | B8: news@canva.com | C8: 5 new templates this week | D8: 6-Newsletters | E8: Low | F8: Archived | G8: Done | I8: =IF(H8="","",ROUND((H8-A8)*24,1)) | J8: =INDEX('Label System'!$F$5:$F$11,MATCH(D8,'Label System'!$A$5:$A$11,0)) -> No reply | K8: =IF(OR(I8="",NOT(ISNUMBER(J8))),"-",IF(I8<=J8,"On time","Late")) -> -
A9: 46293.365 | B9: accounting@batangasbean.ph | C9: Invoice BBT-0923 for coffee beans | D9: 3-Finance | E9: Medium | F9: Saved invoice, forwarded to accounting | G9: Done | H9: 46293.427 | I9: =IF(H9="","",ROUND((H9-A9)*24,1)) -> 1.5 | J9: =INDEX('Label System'!$F$5:$F$11,MATCH(D9,'Label System'!$A$5:$A$11,0)) -> 48 | K9: =IF(OR(I9="",NOT(ISNUMBER(J9))),"-",IF(I9<=J9,"On time","Late")) -> On time
A10: 46293.376 | B10: mark.v@gmail.com | C10: Refund request ORD-10688 | D10: 2-Clients | E10: High | F10: Sent refund steps and return label | G10: Done | H10: 46293.403 | I10: =IF(H10="","",ROUND((H10-A10)*24,1)) -> 0.6 | J10: =INDEX('Label System'!$F$5:$F$11,MATCH(D10,'Label System'!$A$5:$A$11,0)) -> 24 | K10: =IF(OR(I10="",NOT(ISNUMBER(J10))),"-",IF(I10<=J10,"On time","Late")) -> On time
A11: 46293.385 | B11: team@tahanan.ph | C11: Weekly stock count results | D11: 5-Team | E11: Medium | F11: Noted 2 low-stock items, replied | G11: Done | H11: 46293.458 | I11: =IF(H11="","",ROUND((H11-A11)*24,1)) -> 1.8 | J11: =INDEX('Label System'!$F$5:$F$11,MATCH(D11,'Label System'!$A$5:$A$11,0)) -> 24 | K11: =IF(OR(I11="",NOT(ISNUMBER(J11))),"-",IF(I11<=J11,"On time","Late")) -> On time
A12: 46293.396 | B12: alerts@samplebank.ph | C12: Low balance alert | D12: 1-Urgent | E12: High | F12: Flagged to owner by chat and email | G12: Done | H12: 46293.406 | I12: =IF(H12="","",ROUND((H12-A12)*24,1)) -> 0.2 | J12: =INDEX('Label System'!$F$5:$F$11,MATCH(D12,'Label System'!$A$5:$A$11,0)) -> 2 | K12: =IF(OR(I12="",NOT(ISNUMBER(J12))),"-",IF(I12<=J12,"On time","Late")) -> On time
A13: 46293.42 | B13: liza.ramos@gmail.com | C13: Wrong color received | D13: 2-Clients | E13: High | F13: Shipped replacement, replied | G13: Done | H13: 46293.451 | I13: =IF(H13="","",ROUND((H13-A13)*24,1)) -> 0.8 | J13: =INDEX('Label System'!$F$5:$F$11,MATCH(D13,'Label System'!$A$5:$A$11,0)) -> 24 | K13: =IF(OR(I13="",NOT(ISNUMBER(J13))),"-",IF(I13<=J13,"On time","Late")) -> On time
A14: 46293.444 | B14: no-reply@lazada.com.ph | C14: Order cancelled #LZ88213 | D14: 4-Orders | E14: Medium | F14: Updated order tracker | G14: Done | I14: =IF(H14="","",ROUND((H14-A14)*24,1)) | J14: =INDEX('Label System'!$F$5:$F$11,MATCH(D14,'Label System'!$A$5:$A$11,0)) -> Process same day | K14: =IF(OR(I14="",NOT(ISNUMBER(J14))),"-",IF(I14<=J14,"On time","Late")) -> -
A15: 46293.465 | B15: sales@tagaytaydairy.ph | C15: Price increase from October | D15: 3-Finance | E15: Medium | F15: Forwarded to owner for a decision | G15: Waiting | H15: 46293.479 | I15: =IF(H15="","",ROUND((H15-A15)*24,1)) -> 0.3 | J15: =INDEX('Label System'!$F$5:$F$11,MATCH(D15,'Label System'!$A$5:$A$11,0)) -> 48 | K15: =IF(OR(I15="",NOT(ISNUMBER(J15))),"-",IF(I15<=J15,"On time","Late")) -> On time
A16: 46293.49 | B16: promo@lazada.com.ph | C16: 11.11 seller campaign | D16: 6-Newsletters | E16: Low | F16: Archived | G16: Done | I16: =IF(H16="","",ROUND((H16-A16)*24,1)) | J16: =INDEX('Label System'!$F$5:$F$11,MATCH(D16,'Label System'!$A$5:$A$11,0)) -> No reply | K16: =IF(OR(I16="",NOT(ISNUMBER(J16))),"-",IF(I16<=J16,"On time","Late")) -> -
A17: 46293.545 | B17: rotary.cavite@gmail.com | C17: Catering for Oct 12 event | D17: 2-Clients | E17: High | F17: Sent quote, waiting on client | G17: Waiting | H17: 46293.653 | I17: =IF(H17="","",ROUND((H17-A17)*24,1)) -> 2.6 | J17: =INDEX('Label System'!$F$5:$F$11,MATCH(D17,'Label System'!$A$5:$A$11,0)) -> 24 | K17: =IF(OR(I17="",NOT(ISNUMBER(J17))),"-",IF(I17<=J17,"On time","Late")) -> On time
A18: 46293.562 | B18: hr@tahanan.ph | C18: Payroll cutoff reminder | D18: 5-Team | E18: Medium | F18: Added to calendar | G18: Done | H18: 46293.566 | I18: =IF(H18="","",ROUND((H18-A18)*24,1)) -> 0.1 | J18: =INDEX('Label System'!$F$5:$F$11,MATCH(D18,'Label System'!$A$5:$A$11,0)) -> 24 | K18: =IF(OR(I18="",NOT(ISNUMBER(J18))),"-",IF(I18<=J18,"On time","Late")) -> On time
A19: 46293.59 | B19: grace.tan@yahoo.com | C19: Question about bulk discount | D19: 2-Clients | E19: Medium | F19: Checking price list | G19: In progress | I19: =IF(H19="","",ROUND((H19-A19)*24,1)) | J19: =INDEX('Label System'!$F$5:$F$11,MATCH(D19,'Label System'!$A$5:$A$11,0)) -> 24 | K19: =IF(OR(I19="",NOT(ISNUMBER(J19))),"-",IF(I19<=J19,"On time","Late")) -> -
A20: 46293.615 | B20: billing@canva.com | C20: Receipt for Canva Pro | D20: 3-Finance | E20: Low | F20: Saved receipt to Finance folder | G20: Done | I20: =IF(H20="","",ROUND((H20-A20)*24,1)) | J20: =INDEX('Label System'!$F$5:$F$11,MATCH(D20,'Label System'!$A$5:$A$11,0)) -> 48 | K20: =IF(OR(I20="",NOT(ISNUMBER(J20))),"-",IF(I20<=J20,"On time","Late")) -> -
A21: 46293.639 | B21: dizon.events@gmail.com | C21: Re: returned check | D21: 1-Urgent | E21: High | F21: Replied with payment options | G21: Done | H21: 46293.771 | I21: =IF(H21="","",ROUND((H21-A21)*24,1)) -> 3.2 | J21: =INDEX('Label System'!$F$5:$F$11,MATCH(D21,'Label System'!$A$5:$A$11,0)) -> 2 | K21: =IF(OR(I21="",NOT(ISNUMBER(J21))),"-",IF(I21<=J21,"On time","Late")) -> Late
A22: 46293.67 | B22: no-reply@shopee.ph | C22: New order #2409280877 | D22: 4-Orders | E22: Medium | F22: To process tomorrow 8 AM | G22: Not started | I22: =IF(H22="","",ROUND((H22-A22)*24,1)) | J22: =INDEX('Label System'!$F$5:$F$11,MATCH(D22,'Label System'!$A$5:$A$11,0)) -> Process same day | K22: =IF(OR(I22="",NOT(ISNUMBER(J22))),"-",IF(I22<=J22,"On time","Late")) -> -
A23: 46293.688 | B23: jenny.lim@gmail.com | C23: Thank you! | D23: 2-Clients | E23: Low | F23: Replied with thanks | G23: Done | H23: 46293.694 | I23: =IF(H23="","",ROUND((H23-A23)*24,1)) -> 0.2 | J23: =INDEX('Label System'!$F$5:$F$11,MATCH(D23,'Label System'!$A$5:$A$11,0)) -> 24 | K23: =IF(OR(I23="",NOT(ISNUMBER(J23))),"-",IF(I23<=J23,"On time","Late")) -> On time
A24: 46293.715 | B24: team@tahanan.ph | C24: Tomorrow's meeting agenda | D24: 5-Team | E24: Medium | F24: Preparing notes | G24: In progress | I24: =IF(H24="","",ROUND((H24-A24)*24,1)) | J24: =INDEX('Label System'!$F$5:$F$11,MATCH(D24,'Label System'!$A$5:$A$11,0)) -> 24 | K24: =IF(OR(I24="",NOT(ISNUMBER(J24))),"-",IF(I24<=J24,"On time","Late")) -> -
