Workbook

Sheet How it works
A1: Luna & Lace: Monthly Profitability Tracker (September 2026)
A2: Fictional fashion dropshipping store selling in the US, Canada and UK. All data is made up.
A4: Teal headers = data that comes in from Shopify, the ad platforms and the supplier.
A5: Orange headers = calculated with formulas. Flagged orders are highlighted in red on the Orders sheet.
A7: Definitions used in this tracker (all reported in USD):
A8: Gross Sales = Unit Price x Qty
A9: Net Revenue = Gross Sales - Discount - Refund - Chargeback
A10: COGS = (Supplier Cost + Shipping) x Qty. Refunded items keep their COGS: in dropshipping the supplier is not paid back.
A11: Gross Profit = Net Revenue - COGS
A12: Net Profit = Gross Profit - Payment Fees - Ad Spend
A13: Profit Margin = Net Profit / Net Revenue
A14: ROAS (return on ad spend) = Net Revenue / Ad Spend
... A18: Discrepancies: any order that fails a check gets a Flag. Flagged orders are left OUT of the Summary until someone confirms them.

Sheet Rates
A1: Currency | B1: Rate to USD | C1: Note
A2: USD | B2: 1 | C2: Fictional fixed rate for September 2026
A3: CAD | B3: 0.73 | C3: Fictional fixed rate for September 2026
A4: GBP | B4: 1.34 | C4: Fictional fixed rate for September 2026

Sheet Products
A1: SKU | B1: Product | C1: Supplier Cost (USD) | D1: Shipping (USD) | E1: Price USD | F1: Price CAD | G1: Price GBP
A2: LL-101 | B2: Linen Wrap Dress | C2: 14.5 | D2: 4.2 | E2: 49 | F2: 65 | G2: 39
A3: LL-102 | B3: Satin Slip Skirt | C3: 9.8 | D3: 3.1 | E3: 34 | F3: 45 | G3: 27
A4: LL-103 | B4: Oversized Knit Cardigan | C4: 16.2 | D4: 5.4 | E4: 59 | F4: 79 | G4: 47
A5: LL-104 | B5: Wide-Leg Trousers | C5: 11.4 | D5: 3.8 | E5: 42 | F5: 56 | G5: 33
A6: LL-105 | B6: Ribbed Crop Top | C6: 5.6 | D6: 2.2 | E6: 22 | F6: 29 | G6: 18
A7: LL-106 | B7: Faux Leather Tote | C7: 12.9 | D7: 4.6 | E7: 45 | F7: 59 | G7: 36

Sheet Orders
A1: Order ID | B1: Date | C1: Market | D1: Currency | E1: SKU | F1: Qty | G1: Unit Price (local) | H1: Discount (local) | I1: Refund (local) | J1: Chargeback (local) | K1: Payment Fee (local) | L1: Gross Sales (local) | M1: Net Revenue (local) | N1: Rate to USD | O1: Net Revenue (USD) | P1: COGS (USD) | Q1: Payment Fee (USD) | R1: Gross Profit (USD) | S1: Flag
A2: LL-1001 | B2: 46266 | C2: US | D2: USD | E2: LL-103 | F2: 2 | G2: 59 | H2: 0 | I2: 0 | J2: 0 | K2: 3.72 | L2: =G2*F2 -> 118 | M2: =L2-H2-I2-J2 -> 118 | N2: =VLOOKUP(D2,Rates!$A$2:$B$4,2,FALSE) -> 1 | O2: =M2*N2 -> 118 | P2: =IFERROR((VLOOKUP(E2,Products!$A$2:$D$7,3,FALSE)+VLOOKUP(E2,Products!$A$2:$D$7,4,FALSE))*F2,"") -> 43.2 | Q2: =K2*N2 -> 3.72 | R2: =IF(P2="","",O2-P2) -> 74.8 | S2: =IF(COUNTIF($A$2:A2,A2)>1,"Duplicate order ID",IF(D2<>IF(C2="US","USD",IF(C2="CA","CAD","GBP")),"Currency does not match market",IF(F2<=0,"Quantity is 0 or less",IF(ISNA(MATCH(E2,Products!$A$2:$A$7,0)),"SKU not in product list",IF(I2>L2-H2,"Refund bigger than the sale","")))))
A3: LL-1002 | B3: 46266 | C3: UK | D3: GBP | E3: LL-101 | F3: 1 | G3: 39 | H3: 3.9 | I3: 0 | J3: 0 | K3: 1.32 | L3: =G3*F3 -> 39 | M3: =L3-H3-I3-J3 -> 35.1 | N3: =VLOOKUP(D3,Rates!$A$2:$B$4,2,FALSE) -> 1.34 | O3: =M3*N3 -> 47.034 | P3: =IFERROR((VLOOKUP(E3,Products!$A$2:$D$7,3,FALSE)+VLOOKUP(E3,Products!$A$2:$D$7,4,FALSE))*F3,"") -> 18.7 | Q3: =K3*N3 -> 1.7688 | R3: =IF(P3="","",O3-P3) -> 28.334 | S3: =IF(COUNTIF($A$2:A3,A3)>1,"Duplicate order ID",IF(D3<>IF(C3="US","USD",IF(C3="CA","CAD","GBP")),"Currency does not match market",IF(F3<=0,"Quantity is 0 or less",IF(ISNA(MATCH(E3,Products!$A$2:$A$7,0)),"SKU not in product list",IF(I3>L3-H3,"Refund bigger than the sale","")))))
A4: LL-1003 | B4: 46267 | C4: CA | D4: CAD | E4: LL-101 | F4: 2 | G4: 65 | H4: 0 | I4: 0 | J4: 0 | K4: 4.07 | L4: =G4*F4 -> 130 | M4: =L4-H4-I4-J4 -> 130 | N4: =VLOOKUP(D4,Rates!$A$2:$B$4,2,FALSE) -> 0.73 | O4: =M4*N4 -> 94.9 | P4: =IFERROR((VLOOKUP(E4,Products!$A$2:$D$7,3,FALSE)+VLOOKUP(E4,Products!$A$2:$D$7,4,FALSE))*F4,"") -> 37.4 | Q4: =K4*N4 -> 2.9711 | R4: =IF(P4="","",O4-P4) -> 57.5 | S4: =IF(COUNTIF($A$2:A4,A4)>1,"Duplicate order ID",IF(D4<>IF(C4="US","USD",IF(C4="CA","CAD","GBP")),"Currency does not match market",IF(F4<=0,"Quantity is 0 or less",IF(ISNA(MATCH(E4,Products!$A$2:$A$7,0)),"SKU not in product list",IF(I4>L4-H4,"Refund bigger than the sale","")))))
A5: LL-1004 | B5: 46267 | C5: US | D5: USD | E5: LL-103 | F5: 1 | G5: 59 | H5: 0 | I5: 0 | J5: 0 | K5: 2.01 | L5: =G5*F5 -> 59 | M5: =L5-H5-I5-J5 -> 59 | N5: =VLOOKUP(D5,Rates!$A$2:$B$4,2,FALSE) -> 1 | O5: =M5*N5 -> 59 | P5: =IFERROR((VLOOKUP(E5,Products!$A$2:$D$7,3,FALSE)+VLOOKUP(E5,Products!$A$2:$D$7,4,FALSE))*F5,"") -> 21.6 | Q5: =K5*N5 -> 2.01 | R5: =IF(P5="","",O5-P5) -> 37.4 | S5: =IF(COUNTIF($A$2:A5,A5)>1,"Duplicate order ID",IF(D5<>IF(C5="US","USD",IF(C5="CA","CAD","GBP")),"Currency does not match market",IF(F5<=0,"Quantity is 0 or less",IF(ISNA(MATCH(E5,Products!$A$2:$A$7,0)),"SKU not in product list",IF(I5>L5-H5,"Refund bigger than the sale","")))))
A6: LL-1005 | B6: 46268 | C6: US | D6: USD | E6: LL-101 | F6: 2 | G6: 49 | H6: 0 | I6: 0 | J6: 0 | K6: 3.14 | L6: =G6*F6 -> 98 | M6: =L6-H6-I6-J6 -> 98 | N6: =VLOOKUP(D6,Rates!$A$2:$B$4,2,FALSE) -> 1 | O6: =M6*N6 -> 98 | P6: =IFERROR((VLOOKUP(E6,Products!$A$2:$D$7,3,FALSE)+VLOOKUP(E6,Products!$A$2:$D$7,4,FALSE))*F6,"") -> 37.4 | Q6: =K6*N6 -> 3.14 | R6: =IF(P6="","",O6-P6) -> 60.6 | S6: =IF(COUNTIF($A$2:A6,A6)>1,"Duplicate order ID",IF(D6<>IF(C6="US","USD",IF(C6="CA","CAD","GBP")),"Currency does not match market",IF(F6<=0,"Quantity is 0 or less",IF(ISNA(MATCH(E6,Products!$A$2:$A$7,0)),"SKU not in product list",IF(I6>L6-H6,"Refund bigger than the sale","")))))
A7: LL-1006 | B7: 46269 | C7: US | D7: USD | E7: LL-104 | F7: 1 | G7: 42 | H7: 0 | I7: 0 | J7: 0 | K7: 1.52 | L7: =G7*F7 -> 42 | M7: =L7-H7-I7-J7 -> 42 | N7: =VLOOKUP(D7,Rates!$A$2:$B$4,2,FALSE) -> 1 | O7: =M7*N7 -> 42 | P7: =IFERROR((VLOOKUP(E7,Products!$A$2:$D$7,3,FALSE)+VLOOKUP(E7,Products!$A$2:$D$7,4,FALSE))*F7,"") -> 15.2 | Q7: =K7*N7 -> 1.52 | R7: =IF(P7="","",O7-P7) -> 26.8 | S7: =IF(COUNTIF($A$2:A7,A7)>1,"Duplicate order ID",IF(D7<>IF(C7="US","USD",IF(C7="CA","CAD","GBP")),"Currency does not match market",IF(F7<=0,"Quantity is 0 or less",IF(ISNA(MATCH(E7,Products!$A$2:$A$7,0)),"SKU not in product list",IF(I7>L7-H7,"Refund bigger than the sale","")))))
A8: LL-1007 | B8: 46269 | C8: UK | D8: GBP | E8: LL-104 | F8: 1 | G8: 33 | H8: 0 | I8: 16.5 | J8: 0 | K8: 1.26 | L8: =G8*F8 -> 33 | M8: =L8-H8-I8-J8 -> 16.5 | N8: =VLOOKUP(D8,Rates!$A$2:$B$4,2,FALSE) -> 1.34 | O8: =M8*N8 -> 22.11 | P8: =IFERROR((VLOOKUP(E8,Products!$A$2:$D$7,3,FALSE)+VLOOKUP(E8,Products!$A$2:$D$7,4,FALSE))*F8,"") -> 15.2 | Q8: =K8*N8 -> 1.6884 | R8: =IF(P8="","",O8-P8) -> 6.91 | S8: =IF(COUNTIF($A$2:A8,A8)>1,"Duplicate order ID",IF(D8<>IF(C8="US","USD",IF(C8="CA","CAD","GBP")),"Currency does not match market",IF(F8<=0,"Quantity is 0 or less",IF(ISNA(MATCH(E8,Products!$A$2:$A$7,0)),"SKU not in product list",IF(I8>L8-H8,"Refund bigger than the sale","")))))
A9: LL-1008 | B9: 46270 | C9: UK | D9: GBP | E9: LL-104 | F9: 1 | G9: 33 | H9: 3.3 | I9: 0 | J9: 0 | K9: 1.16 | L9: =G9*F9 -> 33 | M9: =L9-H9-I9-J9 -> 29.7 | N9: =VLOOKUP(D9,Rates!$A$2:$B$4,2,FALSE) -> 1.34 | O9: =M9*N9 -> 39.798 | P9: =IFERROR((VLOOKUP(E9,Products!$A$2:$D$7,3,FALSE)+VLOOKUP(E9,Products!$A$2:$D$7,4,FALSE))*F9,"") -> 15.2 | Q9: =K9*N9 -> 1.5544 | R9: =IF(P9="","",O9-P9) -> 24.598 | S9: =IF(COUNTIF($A$2:A9,A9)>1,"Duplicate order ID",IF(D9<>IF(C9="US","USD",IF(C9="CA","CAD","GBP")),"Currency does not match market",IF(F9<=0,"Quantity is 0 or less",IF(ISNA(MATCH(E9,Products!$A$2:$A$7,0)),"SKU not in product list",IF(I9>L9-H9,"Refund bigger than the sale","")))))
A10: LL-1009 | B10: 46270 | C10: CA | D10: CAD | E10: LL-105 | F10: 1 | G10: 29 | H10: 0 | I10: 29 | J10: 0 | K10: 1.14 | L10: =G10*F10 -> 29 | M10: =L10-H10-I10-J10 -> 0 | N10: =VLOOKUP(D10,Rates!$A$2:$B$4,2,FALSE) -> 0.73 | O10: =M10*N10 -> 0 | P10: =IFERROR((VLOOKUP(E10,Products!$A$2:$D$7,3,FALSE)+VLOOKUP(E10,Products!$A$2:$D$7,4,FALSE))*F10,"") -> 7.8 | Q10: =K10*N10 -> 0.8322 | R10: =IF(P10="","",O10-P10) -> -7.8 | S10: =IF(COUNTIF($A$2:A10,A10)>1,"Duplicate order ID",IF(D10<>IF(C10="US","USD",IF(C10="CA","CAD","GBP")),"Currency does not match market",IF(F10<=0,"Quantity is 0 or less",IF(ISNA(MATCH(E10,Products!$A$2:$A$7,0)),"SKU not in product list",IF(I10>L10-H10,"Refund bigger than the sale","")))))
A11: LL-1010 | B11: 46271 | C11: UK | D11: GBP | E11: LL-105 | F11: 1 | G11: 18 | H11: 0 | I11: 0 | J11: 0 | K11: 0.82 | L11: =G11*F11 -> 18 | M11: =L11-H11-I11-J11 -> 18 | N11: =VLOOKUP(D11,Rates!$A$2:$B$4,2,FALSE) -> 1.34 | O11: =M11*N11 -> 24.12 | P11: =IFERROR((VLOOKUP(E11,Products!$A$2:$D$7,3,FALSE)+VLOOKUP(E11,Products!$A$2:$D$7,4,FALSE))*F11,"") -> 7.8 | Q11: =K11*N11 -> 1.0988 | R11: =IF(P11="","",O11-P11) -> 16.32 | S11: =IF(COUNTIF($A$2:A11,A11)>1,"Duplicate order ID",IF(D11<>IF(C11="US","USD",IF(C11="CA","CAD","GBP")),"Currency does not match market",IF(F11<=0,"Quantity is 0 or less",IF(ISNA(MATCH(E11,Products!$A$2:$A$7,0)),"SKU not in product list",IF(I11>L11-H11,"Refund bigger than the sale","")))))
A12: LL-1010 | B12: 46271 | C12: UK | D12: GBP | E12: LL-105 | F12: 1 | G12: 18 | H12: 0 | I12: 0 | J12: 0 | K12: 0.82 | L12: =G12*F12 -> 18 | M12: =L12-H12-I12-J12 -> 18 | N12: =VLOOKUP(D12,Rates!$A$2:$B$4,2,FALSE) -> 1.34 | O12: =M12*N12 -> 24.12 | P12: =IFERROR((VLOOKUP(E12,Products!$A$2:$D$7,3,FALSE)+VLOOKUP(E12,Products!$A$2:$D$7,4,FALSE))*F12,"") -> 7.8 | Q12: =K12*N12 -> 1.0988 | R12: =IF(P12="","",O12-P12) -> 16.32 | S12: =IF(COUNTIF($A$2:A12,A12)>1,"Duplicate order ID",IF(D12<>IF(C12="US","USD",IF(C12="CA","CAD","GBP")),"Currency does not match market",IF(F12<=0,"Quantity is 0 or less",IF(ISNA(MATCH(E12,Products!$A$2:$A$7,0)),"SKU not in product list",IF(I12>L12-H12,"Refund bigger than the sale",""))))) -> Duplicate order ID
A13: LL-1011 | B13: 46272 | C13: CA | D13: CAD | E13: LL-102 | F13: 1 | G13: 45 | H13: 0 | I13: 0 | J13: 0 | K13: 1.61 | L13: =G13*F13 -> 45 | M13: =L13-H13-I13-J13 -> 45 | N13: =VLOOKUP(D13,Rates!$A$2:$B$4,2,FALSE) -> 0.73 | O13: =M13*N13 -> 32.85 | P13: =IFERROR((VLOOKUP(E13,Products!$A$2:$D$7,3,FALSE)+VLOOKUP(E13,Products!$A$2:$D$7,4,FALSE))*F13,"") -> 12.9 | Q13: =K13*N13 -> 1.1753 | R13: =IF(P13="","",O13-P13) -> 19.95 | S13: =IF(COUNTIF($A$2:A13,A13)>1,"Duplicate order ID",IF(D13<>IF(C13="US","USD",IF(C13="CA","CAD","GBP")),"Currency does not match market",IF(F13<=0,"Quantity is 0 or less",IF(ISNA(MATCH(E13,Products!$A$2:$A$7,0)),"SKU not in product list",IF(I13>L13-H13,"Refund bigger than the sale","")))))
... A50: LL-1048 | B50: 46295 | C50: US | D50: USD | E50: LL-102 | F50: 2 | G50: 34 | H50: 0 | I50: 0 | J50: 0 | K50: 2.27 | L50: =G50*F50 -> 68 | M50: =L50-H50-I50-J50 -> 68 | N50: =VLOOKUP(D50,Rates!$A$2:$B$4,2,FALSE) -> 1 | O50: =M50*N50 -> 68 | P50: =IFERROR((VLOOKUP(E50,Products!$A$2:$D$7,3,FALSE)+VLOOKUP(E50,Products!$A$2:$D$7,4,FALSE))*F50,"") -> 25.8 | Q50: =K50*N50 -> 2.27 | R50: =IF(P50="","",O50-P50) -> 42.2 | S50: =IF(COUNTIF($A$2:A50,A50)>1,"Duplicate order ID",IF(D50<>IF(C50="US","USD",IF(C50="CA","CAD","GBP")),"Currency does not match market",IF(F50<=0,"Quantity is 0 or less",IF(ISNA(MATCH(E50,Products!$A$2:$A$7,0)),"SKU not in product list",IF(I50>L50-H50,"Refund bigger than the sale","")))))

Sheet Ads
A1: Week | B1: Market | C1: Platform | D1: Currency | E1: Spend (local) | F1: Rate to USD | G1: Spend (USD)
A2: Week 1 | B2: US | C2: Meta | D2: USD | E2: 48.74 | F2: =VLOOKUP(D2,Rates!$A$2:$B$4,2,FALSE) -> 1 | G2: =E2*F2 -> 48.74
A3: Week 1 | B3: US | C3: TikTok | D3: USD | E3: 22.13 | F3: =VLOOKUP(D3,Rates!$A$2:$B$4,2,FALSE) -> 1 | G3: =E3*F3 -> 22.13
A4: Week 1 | B4: CA | C4: Meta | D4: CAD | E4: 31.87 | F4: =VLOOKUP(D4,Rates!$A$2:$B$4,2,FALSE) -> 0.73 | G4: =E4*F4 -> 23.2651
A5: Week 1 | B5: CA | C5: TikTok | D5: CAD | E5: 15.27 | F5: =VLOOKUP(D5,Rates!$A$2:$B$4,2,FALSE) -> 0.73 | G5: =E5*F5 -> 11.1471
A6: Week 1 | B6: UK | C6: Meta | D6: GBP | E6: 47.45 | F6: =VLOOKUP(D6,Rates!$A$2:$B$4,2,FALSE) -> 1.34 | G6: =E6*F6 -> 63.583
A7: Week 1 | B7: UK | C7: TikTok | D7: GBP | E7: 34.56 | F7: =VLOOKUP(D7,Rates!$A$2:$B$4,2,FALSE) -> 1.34 | G7: =E7*F7 -> 46.3104
A8: Week 2 | B8: US | C8: Meta | D8: USD | E8: 65.29 | F8: =VLOOKUP(D8,Rates!$A$2:$B$4,2,FALSE) -> 1 | G8: =E8*F8 -> 65.29
A9: Week 2 | B9: US | C9: TikTok | D9: USD | E9: 26.13 | F9: =VLOOKUP(D9,Rates!$A$2:$B$4,2,FALSE) -> 1 | G9: =E9*F9 -> 26.13
A10: Week 2 | B10: CA | C10: Meta | D10: CAD | E10: 26.4 | F10: =VLOOKUP(D10,Rates!$A$2:$B$4,2,FALSE) -> 0.73 | G10: =E10*F10 -> 19.272
A11: Week 2 | B11: CA | C11: TikTok | D11: CAD | E11: 15.81 | F11: =VLOOKUP(D11,Rates!$A$2:$B$4,2,FALSE) -> 0.73 | G11: =E11*F11 -> 11.5413
A12: Week 2 | B12: UK | C12: Meta | D12: GBP | E12: 48.35 | F12: =VLOOKUP(D12,Rates!$A$2:$B$4,2,FALSE) -> 1.34 | G12: =E12*F12 -> 64.789
A13: Week 2 | B13: UK | C13: TikTok | D13: GBP | E13: 29.06 | F13: =VLOOKUP(D13,Rates!$A$2:$B$4,2,FALSE) -> 1.34 | G13: =E13*F13 -> 38.9404
... A25: Week 4 | B25: UK | C25: TikTok | D25: GBP | E25: 32.63 | F25: =VLOOKUP(D25,Rates!$A$2:$B$4,2,FALSE) -> 1.34 | G25: =E25*F25 -> 43.7242

Sheet Summary
A1: Metric (USD) | B1: US | C1: CA | D1: UK | E1: Total
A2: Gross Sales | B2: =SUMPRODUCT((Orders!$C$2:$C$50=B$1)*(Orders!$S$2:$S$50="")*Orders!$L$2:$L$50*Orders!$N$2:$N$50) -> 1617 | C2: =SUMPRODUCT((Orders!$C$2:$C$50=C$1)*(Orders!$S$2:$S$50="")*Orders!$L$2:$L$50*Orders!$N$2:$N$50) -> 593.49 | D2: =SUMPRODUCT((Orders!$C$2:$C$50=D$1)*(Orders!$S$2:$S$50="")*Orders!$L$2:$L$50*Orders!$N$2:$N$50) -> 426.12 | E2: =SUM(B2:D2) -> 2636.61
A3: Discounts | B3: =SUMPRODUCT((Orders!$C$2:$C$50=B$1)*(Orders!$S$2:$S$50="")*Orders!$H$2:$H$50*Orders!$N$2:$N$50) -> 17.4 | C3: =SUMPRODUCT((Orders!$C$2:$C$50=C$1)*(Orders!$S$2:$S$50="")*Orders!$H$2:$H$50*Orders!$N$2:$N$50) -> 5.767 | D3: =SUMPRODUCT((Orders!$C$2:$C$50=D$1)*(Orders!$S$2:$S$50="")*Orders!$H$2:$H$50*Orders!$N$2:$N$50) -> 9.648 | E3: =SUM(B3:D3) -> 32.815
A4: Refunds | B4: =SUMPRODUCT((Orders!$C$2:$C$50=B$1)*(Orders!$S$2:$S$50="")*Orders!$I$2:$I$50*Orders!$N$2:$N$50) -> 208 | C4: =SUMPRODUCT((Orders!$C$2:$C$50=C$1)*(Orders!$S$2:$S$50="")*Orders!$I$2:$I$50*Orders!$N$2:$N$50) -> 21.17 | D4: =SUMPRODUCT((Orders!$C$2:$C$50=D$1)*(Orders!$S$2:$S$50="")*Orders!$I$2:$I$50*Orders!$N$2:$N$50) -> 22.11 | E4: =SUM(B4:D4) -> 251.28
A5: Chargebacks | B5: =SUMPRODUCT((Orders!$C$2:$C$50=B$1)*(Orders!$S$2:$S$50="")*Orders!$J$2:$J$50*Orders!$N$2:$N$50) -> 78.1 | C5: =SUMPRODUCT((Orders!$C$2:$C$50=C$1)*(Orders!$S$2:$S$50="")*Orders!$J$2:$J$50*Orders!$N$2:$N$50) -> 0 | D5: =SUMPRODUCT((Orders!$C$2:$C$50=D$1)*(Orders!$S$2:$S$50="")*Orders!$J$2:$J$50*Orders!$N$2:$N$50) -> 0 | E5: =SUM(B5:D5) -> 78.1
A6: Net Revenue | B6: =B2-B3-B4-B5 -> 1313.5 | C6: =C2-C3-C4-C5 -> 566.553 | D6: =D2-D3-D4-D5 -> 394.362 | E6: =E2-E3-E4-E5 -> 2274.415
A7: COGS | B7: =SUMIFS(Orders!$P$2:$P$50,Orders!$C$2:$C$50,B$1,Orders!$S$2:$S$50,"") -> 600.9 | C7: =SUMIFS(Orders!$P$2:$P$50,Orders!$C$2:$C$50,C$1,Orders!$S$2:$S$50,"") -> 228.1 | D7: =SUMIFS(Orders!$P$2:$P$50,Orders!$C$2:$C$50,D$1,Orders!$S$2:$S$50,"") -> 147.5 | E7: =SUM(B7:D7) -> 976.5
A8: Gross Profit | B8: =B6-B7 -> 712.6 | C8: =C6-C7 -> 338.453 | D8: =D6-D7 -> 246.862 | E8: =E6-E7 -> 1297.915
A9: Payment Fees | B9: =SUMIFS(Orders!$Q$2:$Q$50,Orders!$C$2:$C$50,B$1,Orders!$S$2:$S$50,"") -> 54.22 | C9: =SUMIFS(Orders!$Q$2:$Q$50,Orders!$C$2:$C$50,C$1,Orders!$S$2:$S$50,"") -> 19.2428 | D9: =SUMIFS(Orders!$Q$2:$Q$50,Orders!$C$2:$C$50,D$1,Orders!$S$2:$S$50,"") -> 15.2894 | E9: =SUM(B9:D9) -> 88.7522
A10: Ad Spend | B10: =SUMIFS(Ads!$G$2:$G$25,Ads!$B$2:$B$25,B$1) -> 323.36 | C10: =SUMIFS(Ads!$G$2:$G$25,Ads!$B$2:$B$25,C$1) -> 132.9987 | D10: =SUMIFS(Ads!$G$2:$G$25,Ads!$B$2:$B$25,D$1) -> 429.5906 | E10: =SUM(B10:D10) -> 885.9493
A11: Net Profit | B11: =B8-B9-B10 -> 335.02 | C11: =C8-C9-C10 -> 186.2115 | D11: =D8-D9-D10 -> -198.018 | E11: =E8-E9-E10 -> 323.2135
A12: Profit Margin | B12: =IF(B6=0,0,B11/B6) -> 0.255059 | C12: =IF(C6=0,0,C11/C6) -> 0.32867446 | D12: =IF(D6=0,0,D11/D6) -> -0.50212242 | E12: =IF(E6=0,0,E11/E6) -> 0.14210841
A13: ROAS | B13: =IF(B10=0,0,B6/B10) -> 4.0620361 | C13: =IF(C10=0,0,C6/C10) -> 4.2598386 | D13: =IF(D10=0,0,D6/D10) -> 0.91799495 | E13: =IF(E10=0,0,E6/E10) -> 2.5672067
A14: POAS | B14: =IF(B10=0,0,B8/B10) -> 2.2037358 | C14: =IF(C10=0,0,C8/C10) -> 2.5447843 | D14: =IF(D10=0,0,D8/D10) -> 0.57464479 | E14: =IF(E10=0,0,E8/E10) -> 1.4649992
A15: Flagged orders (count) | B15: =SUMPRODUCT((Orders!$C$2:$C$50=B$1)*(Orders!$S$2:$S$50<>"")) -> 1 | C15: =SUMPRODUCT((Orders!$C$2:$C$50=C$1)*(Orders!$S$2:$S$50<>"")) -> 1 | D15: =SUMPRODUCT((Orders!$C$2:$C$50=D$1)*(Orders!$S$2:$S$50<>"")) -> 3 | E15: =SUM(B15:D15) -> 5
A17: Flagged orders are left out of every number above until someone confirms them (see the Flag column on Orders).
